MANIFEST.in
README
setup.py
CodernityDB/__init__.py
CodernityDB/database.py
CodernityDB/database_gevent.py
CodernityDB/database_safe_shared.py
CodernityDB/database_super_thread_safe.py
CodernityDB/database_thread_safe.py
CodernityDB/debug_stuff.py
CodernityDB/env.py
CodernityDB/hash_index.py
CodernityDB/index.py
CodernityDB/indexcreator.py
CodernityDB/lfu_cache.py
CodernityDB/lfu_cache_with_lock.py
CodernityDB/migrate.py
CodernityDB/misc.py
CodernityDB/patch.py
CodernityDB/rr_cache.py
CodernityDB/rr_cache_with_lock.py
CodernityDB/sharded_hash.py
CodernityDB/sharded_index.py
CodernityDB/storage.py
CodernityDB/tree_index.py
CodernityDB.egg-info/PKG-INFO
CodernityDB.egg-info/SOURCES.txt
CodernityDB.egg-info/dependency_links.txt
CodernityDB.egg-info/top_level.txt