Metadata-Version: 1.1
Name: CodernityDB
Version: 0.4.0
Summary: Pure python, fast, schema-less, NoSQL database
Home-page: http://labs.codernity.com/codernitydb
Author: Codernity
Author-email: contact@codernity.com
License: Apache 2.0
Platform: any
Classifier: License :: OSI Approved :: Apache Software License
Classifier: Programming Language :: Python :: 2.6
Classifier: Programming Language :: Python :: 2.7
Classifier: Operating System :: MacOS :: MacOS X
Classifier: Operating System :: POSIX
Classifier: Operating System :: Microsoft :: Windows
Classifier: Operating System :: OS Independent
Classifier: Topic :: Internet
Classifier: Topic :: Database
Classifier: Topic :: Software Development
Classifier: Intended Audience :: Developers
Classifier: Development Status :: 4 - Beta
